{"$schema":"http://cyclonedx.org/schema/bom-1.5.schema.json","bomFormat":"CycloneDX","specVersion":"1.5","serialNumber":"urn:uuid:9fbfba34-27b6-46b3-b9d7-bd32e516715a","version":1,"metadata":{"timestamp":"2024-08-02T09:58:46+02:00","tools":{"components":[{"type":"application","author":"anchore","name":"syft","version":"1.4.1"}]},"component":{"bom-ref":"d6f50aa3ff6a6212","type":"file","name":"/Users/massimocoppolaro/Desktop/Università/Tirocinio2.0/Software/UA-.NETStandard"}},"components":[{"bom-ref":"pkg:github/actions/checkout@v4?package-id=b5f350d6226729f2","type":"library","name":"actions/checkout","version":"v4","cpe":"cpe:2.3:a:actions\\/checkout:actions\\/checkout:v4:*:*:*:*:*:*:*","purl":"pkg:github/actions/checkout@v4","properties":[{"name":"syft:package:foundBy","value":"github-actions-usage-cataloger"},{"name":"syft:package:type","value":"github-action"},{"name":"syft:location:0:path","value":"/.github/workflows/buildandtest.yml"}]},{"bom-ref":"pkg:github/actions/checkout@v4?package-id=79f78bdf57d9336e","type":"library","name":"actions/checkout","version":"v4","cpe":"cpe:2.3:a:actions\\/checkout:actions\\/checkout:v4:*:*:*:*:*:*:*","purl":"pkg:github/actions/checkout@v4","properties":[{"name":"syft:package:foundBy","value":"github-actions-usage-cataloger"},{"name":"syft:package:type","value":"github-action"},{"name":"syft:location:0:path","value":"/.github/workflows/codeql-analysis.yml"}]},{"bom-ref":"pkg:github/actions/checkout@v4?package-id=01ea018f9f80881e","type":"library","name":"actions/checkout","version":"v4","cpe":"cpe:2.3:a:actions\\/checkout:actions\\/checkout:v4:*:*:*:*:*:*:*","purl":"pkg:github/actions/checkout@v4","properties":[{"name":"syft:package:foundBy","value":"github-actions-usage-cataloger"},{"name":"syft:package:type","value":"github-action"},{"name":"syft:location:0:path","value":"/.github/workflows/docker-image.yml"}]},{"bom-ref":"pkg:github/actions/setup-dotnet@v4?package-id=9d79e7a3c3f9de16","type":"library","name":"actions/setup-dotnet","version":"v4","cpe":"cpe:2.3:a:actions\\/setup-dotnet:actions\\/setup-dotnet:v4:*:*:*:*:*:*:*","purl":"pkg:github/actions/setup-dotnet@v4","properties":[{"name":"syft:package:foundBy","value":"github-actions-usage-cataloger"},{"name":"syft:package:type","value":"github-action"},{"name":"syft:cpe23","value":"cpe:2.3:a:actions\\/setup-dotnet:actions\\/setup_dotnet:v4:*:*:*:*:*:*:*"},{"name":"syft:cpe23","value":"cpe:2.3:a:actions\\/setup_dotnet:actions\\/setup-dotnet:v4:*:*:*:*:*:*:*"},{"name":"syft:cpe23","value":"cpe:2.3:a:actions\\/setup_dotnet:actions\\/setup_dotnet:v4:*:*:*:*:*:*:*"},{"name":"syft:cpe23","value":"cpe:2.3:a:actions\\/setup:actions\\/setup-dotnet:v4:*:*:*:*:*:*:*"},{"name":"syft:cpe23","value":"cpe:2.3:a:actions\\/setup:actions\\/setup_dotnet:v4:*:*:*:*:*:*:*"},{"name":"syft:location:0:path","value":"/.github/workflows/buildandtest.yml"}]},{"bom-ref":"pkg:github/actions/setup-dotnet@v4?package-id=00aec27ed7e36932","type":"library","name":"actions/setup-dotnet","version":"v4","cpe":"cpe:2.3:a:actions\\/setup-dotnet:actions\\/setup-dotnet:v4:*:*:*:*:*:*:*","purl":"pkg:github/actions/setup-dotnet@v4","properties":[{"name":"syft:package:foundBy","value":"github-actions-usage-cataloger"},{"name":"syft:package:type","value":"github-action"},{"name":"syft:cpe23","value":"cpe:2.3:a:actions\\/setup-dotnet:actions\\/setup_dotnet:v4:*:*:*:*:*:*:*"},{"name":"syft:cpe23","value":"cpe:2.3:a:actions\\/setup_dotnet:actions\\/setup-dotnet:v4:*:*:*:*:*:*:*"},{"name":"syft:cpe23","value":"cpe:2.3:a:actions\\/setup_dotnet:actions\\/setup_dotnet:v4:*:*:*:*:*:*:*"},{"name":"syft:cpe23","value":"cpe:2.3:a:actions\\/setup:actions\\/setup-dotnet:v4:*:*:*:*:*:*:*"},{"name":"syft:cpe23","value":"cpe:2.3:a:actions\\/setup:actions\\/setup_dotnet:v4:*:*:*:*:*:*:*"},{"name":"syft:location:0:path","value":"/.github/workflows/codeql-analysis.yml"}]},{"bom-ref":"pkg:github/actions/setup-dotnet@v4?package-id=6660bc0773c21d84","type":"library","name":"actions/setup-dotnet","version":"v4","cpe":"cpe:2.3:a:actions\\/setup-dotnet:actions\\/setup-dotnet:v4:*:*:*:*:*:*:*","purl":"pkg:github/actions/setup-dotnet@v4","properties":[{"name":"syft:package:foundBy","value":"github-actions-usage-cataloger"},{"name":"syft:package:type","value":"github-action"},{"name":"syft:cpe23","value":"cpe:2.3:a:actions\\/setup-dotnet:actions\\/setup_dotnet:v4:*:*:*:*:*:*:*"},{"name":"syft:cpe23","value":"cpe:2.3:a:actions\\/setup_dotnet:actions\\/setup-dotnet:v4:*:*:*:*:*:*:*"},{"name":"syft:cpe23","value":"cpe:2.3:a:actions\\/setup_dotnet:actions\\/setup_dotnet:v4:*:*:*:*:*:*:*"},{"name":"syft:cpe23","value":"cpe:2.3:a:actions\\/setup:actions\\/setup-dotnet:v4:*:*:*:*:*:*:*"},{"name":"syft:cpe23","value":"cpe:2.3:a:actions\\/setup:actions\\/setup_dotnet:v4:*:*:*:*:*:*:*"},{"name":"syft:location:0:path","value":"/.github/workflows/docker-image.yml"}]},{"bom-ref":"pkg:github/actions/upload-artifact@v4?package-id=dbbca00a8a5b5873","type":"library","name":"actions/upload-artifact","version":"v4","cpe":"cpe:2.3:a:actions\\/upload-artifact:actions\\/upload-artifact:v4:*:*:*:*:*:*:*","purl":"pkg:github/actions/upload-artifact@v4","properties":[{"name":"syft:package:foundBy","value":"github-actions-usage-cataloger"},{"name":"syft:package:type","value":"github-action"},{"name":"syft:cpe23","value":"cpe:2.3:a:actions\\/upload-artifact:actions\\/upload_artifact:v4:*:*:*:*:*:*:*"},{"name":"syft:cpe23","value":"cpe:2.3:a:actions\\/upload_artifact:actions\\/upload-artifact:v4:*:*:*:*:*:*:*"},{"name":"syft:cpe23","value":"cpe:2.3:a:actions\\/upload_artifact:actions\\/upload_artifact:v4:*:*:*:*:*:*:*"},{"name":"syft:cpe23","value":"cpe:2.3:a:actions\\/upload:actions\\/upload-artifact:v4:*:*:*:*:*:*:*"},{"name":"syft:cpe23","value":"cpe:2.3:a:actions\\/upload:actions\\/upload_artifact:v4:*:*:*:*:*:*:*"},{"name":"syft:location:0:path","value":"/.github/workflows/buildandtest.yml"}]},{"bom-ref":"pkg:github/codecov/codecov-action@v4?package-id=54187d8e1f20751a","type":"library","name":"codecov/codecov-action","version":"v4","cpe":"cpe:2.3:a:codecov\\/codecov-action:codecov\\/codecov-action:v4:*:*:*:*:*:*:*","purl":"pkg:github/codecov/codecov-action@v4","properties":[{"name":"syft:package:foundBy","value":"github-actions-usage-cataloger"},{"name":"syft:package:type","value":"github-action"},{"name":"syft:cpe23","value":"cpe:2.3:a:codecov\\/codecov-action:codecov\\/codecov_action:v4:*:*:*:*:*:*:*"},{"name":"syft:cpe23","value":"cpe:2.3:a:codecov\\/codecov_action:codecov\\/codecov-action:v4:*:*:*:*:*:*:*"},{"name":"syft:cpe23","value":"cpe:2.3:a:codecov\\/codecov_action:codecov\\/codecov_action:v4:*:*:*:*:*:*:*"},{"name":"syft:cpe23","value":"cpe:2.3:a:codecov\\/codecov:codecov\\/codecov-action:v4:*:*:*:*:*:*:*"},{"name":"syft:cpe23","value":"cpe:2.3:a:codecov\\/codecov:codecov\\/codecov_action:v4:*:*:*:*:*:*:*"},{"name":"syft:location:0:path","value":"/.github/workflows/buildandtest.yml"}]},{"bom-ref":"pkg:github/docker/build-push-action@v6?package-id=818d252784754f1a","type":"library","name":"docker/build-push-action","version":"v6","cpe":"cpe:2.3:a:docker\\/build-push-action:docker\\/build-push-action:v6:*:*:*:*:*:*:*","purl":"pkg:github/docker/build-push-action@v6","properties":[{"name":"syft:package:foundBy","value":"github-actions-usage-cataloger"},{"name":"syft:package:type","value":"github-action"},{"name":"syft:cpe23","value":"cpe:2.3:a:docker\\/build-push-action:docker\\/build_push_action:v6:*:*:*:*:*:*:*"},{"name":"syft:cpe23","value":"cpe:2.3:a:docker\\/build_push_action:docker\\/build-push-action:v6:*:*:*:*:*:*:*"},{"name":"syft:cpe23","value":"cpe:2.3:a:docker\\/build_push_action:docker\\/build_push_action:v6:*:*:*:*:*:*:*"},{"name":"syft:cpe23","value":"cpe:2.3:a:docker\\/build-push:docker\\/build-push-action:v6:*:*:*:*:*:*:*"},{"name":"syft:cpe23","value":"cpe:2.3:a:docker\\/build-push:docker\\/build_push_action:v6:*:*:*:*:*:*:*"},{"name":"syft:cpe23","value":"cpe:2.3:a:docker\\/build_push:docker\\/build-push-action:v6:*:*:*:*:*:*:*"},{"name":"syft:cpe23","value":"cpe:2.3:a:docker\\/build_push:docker\\/build_push_action:v6:*:*:*:*:*:*:*"},{"name":"syft:cpe23","value":"cpe:2.3:a:docker\\/build:docker\\/build-push-action:v6:*:*:*:*:*:*:*"},{"name":"syft:cpe23","value":"cpe:2.3:a:docker\\/build:docker\\/build_push_action:v6:*:*:*:*:*:*:*"},{"name":"syft:location:0:path","value":"/.github/workflows/docker-image.yml"}]},{"bom-ref":"pkg:github/docker/login-action@v3?package-id=1aa9d05cfbcf7fe0","type":"library","name":"docker/login-action","version":"v3","cpe":"cpe:2.3:a:docker\\/login-action:docker\\/login-action:v3:*:*:*:*:*:*:*","purl":"pkg:github/docker/login-action@v3","properties":[{"name":"syft:package:foundBy","value":"github-actions-usage-cataloger"},{"name":"syft:package:type","value":"github-action"},{"name":"syft:cpe23","value":"cpe:2.3:a:docker\\/login-action:docker\\/login_action:v3:*:*:*:*:*:*:*"},{"name":"syft:cpe23","value":"cpe:2.3:a:docker\\/login_action:docker\\/login-action:v3:*:*:*:*:*:*:*"},{"name":"syft:cpe23","value":"cpe:2.3:a:docker\\/login_action:docker\\/login_action:v3:*:*:*:*:*:*:*"},{"name":"syft:cpe23","value":"cpe:2.3:a:docker\\/login:docker\\/login-action:v3:*:*:*:*:*:*:*"},{"name":"syft:cpe23","value":"cpe:2.3:a:docker\\/login:docker\\/login_action:v3:*:*:*:*:*:*:*"},{"name":"syft:location:0:path","value":"/.github/workflows/docker-image.yml"}]},{"bom-ref":"pkg:github/docker/metadata-action@v5?package-id=d5bd03cca69fdaea","type":"library","name":"docker/metadata-action","version":"v5","cpe":"cpe:2.3:a:docker\\/metadata-action:docker\\/metadata-action:v5:*:*:*:*:*:*:*","purl":"pkg:github/docker/metadata-action@v5","properties":[{"name":"syft:package:foundBy","value":"github-actions-usage-cataloger"},{"name":"syft:package:type","value":"github-action"},{"name":"syft:cpe23","value":"cpe:2.3:a:docker\\/metadata-action:docker\\/metadata_action:v5:*:*:*:*:*:*:*"},{"name":"syft:cpe23","value":"cpe:2.3:a:docker\\/metadata_action:docker\\/metadata-action:v5:*:*:*:*:*:*:*"},{"name":"syft:cpe23","value":"cpe:2.3:a:docker\\/metadata_action:docker\\/metadata_action:v5:*:*:*:*:*:*:*"},{"name":"syft:cpe23","value":"cpe:2.3:a:docker\\/metadata:docker\\/metadata-action:v5:*:*:*:*:*:*:*"},{"name":"syft:cpe23","value":"cpe:2.3:a:docker\\/metadata:docker\\/metadata_action:v5:*:*:*:*:*:*:*"},{"name":"syft:location:0:path","value":"/.github/workflows/docker-image.yml"}]},{"bom-ref":"pkg:github/docker/setup-buildx-action@v3?package-id=c8a2815dc05878bc","type":"library","name":"docker/setup-buildx-action","version":"v3","cpe":"cpe:2.3:a:docker\\/setup-buildx-action:docker\\/setup-buildx-action:v3:*:*:*:*:*:*:*","purl":"pkg:github/docker/setup-buildx-action@v3","properties":[{"name":"syft:package:foundBy","value":"github-actions-usage-cataloger"},{"name":"syft:package:type","value":"github-action"},{"name":"syft:cpe23","value":"cpe:2.3:a:docker\\/setup-buildx-action:docker\\/setup_buildx_action:v3:*:*:*:*:*:*:*"},{"name":"syft:cpe23","value":"cpe:2.3:a:docker\\/setup_buildx_action:docker\\/setup-buildx-action:v3:*:*:*:*:*:*:*"},{"name":"syft:cpe23","value":"cpe:2.3:a:docker\\/setup_buildx_action:docker\\/setup_buildx_action:v3:*:*:*:*:*:*:*"},{"name":"syft:cpe23","value":"cpe:2.3:a:docker\\/setup-buildx:docker\\/setup-buildx-action:v3:*:*:*:*:*:*:*"},{"name":"syft:cpe23","value":"cpe:2.3:a:docker\\/setup-buildx:docker\\/setup_buildx_action:v3:*:*:*:*:*:*:*"},{"name":"syft:cpe23","value":"cpe:2.3:a:docker\\/setup_buildx:docker\\/setup-buildx-action:v3:*:*:*:*:*:*:*"},{"name":"syft:cpe23","value":"cpe:2.3:a:docker\\/setup_buildx:docker\\/setup_buildx_action:v3:*:*:*:*:*:*:*"},{"name":"syft:cpe23","value":"cpe:2.3:a:docker\\/setup:docker\\/setup-buildx-action:v3:*:*:*:*:*:*:*"},{"name":"syft:cpe23","value":"cpe:2.3:a:docker\\/setup:docker\\/setup_buildx_action:v3:*:*:*:*:*:*:*"},{"name":"syft:location:0:path","value":"/.github/workflows/docker-image.yml"}]},{"bom-ref":"pkg:github/docker/setup-qemu-action@v3?package-id=eb30565ef2d5da03","type":"library","name":"docker/setup-qemu-action","version":"v3","cpe":"cpe:2.3:a:docker\\/setup-qemu-action:docker\\/setup-qemu-action:v3:*:*:*:*:*:*:*","purl":"pkg:github/docker/setup-qemu-action@v3","properties":[{"name":"syft:package:foundBy","value":"github-actions-usage-cataloger"},{"name":"syft:package:type","value":"github-action"},{"name":"syft:cpe23","value":"cpe:2.3:a:docker\\/setup-qemu-action:docker\\/setup_qemu_action:v3:*:*:*:*:*:*:*"},{"name":"syft:cpe23","value":"cpe:2.3:a:docker\\/setup_qemu_action:docker\\/setup-qemu-action:v3:*:*:*:*:*:*:*"},{"name":"syft:cpe23","value":"cpe:2.3:a:docker\\/setup_qemu_action:docker\\/setup_qemu_action:v3:*:*:*:*:*:*:*"},{"name":"syft:cpe23","value":"cpe:2.3:a:docker\\/setup-qemu:docker\\/setup-qemu-action:v3:*:*:*:*:*:*:*"},{"name":"syft:cpe23","value":"cpe:2.3:a:docker\\/setup-qemu:docker\\/setup_qemu_action:v3:*:*:*:*:*:*:*"},{"name":"syft:cpe23","value":"cpe:2.3:a:docker\\/setup_qemu:docker\\/setup-qemu-action:v3:*:*:*:*:*:*:*"},{"name":"syft:cpe23","value":"cpe:2.3:a:docker\\/setup_qemu:docker\\/setup_qemu_action:v3:*:*:*:*:*:*:*"},{"name":"syft:cpe23","value":"cpe:2.3:a:docker\\/setup:docker\\/setup-qemu-action:v3:*:*:*:*:*:*:*"},{"name":"syft:cpe23","value":"cpe:2.3:a:docker\\/setup:docker\\/setup_qemu_action:v3:*:*:*:*:*:*:*"},{"name":"syft:location:0:path","value":"/.github/workflows/docker-image.yml"}]},{"bom-ref":"pkg:github/github/codeql-action@v3?package-id=3f7e1d064db22120#analyze","type":"library","name":"github/codeql-action/analyze","version":"v3","cpe":"cpe:2.3:a:github\\/codeql-action\\/analyze:github\\/codeql-action\\/analyze:v3:*:*:*:*:*:*:*","purl":"pkg:github/github/codeql-action@v3#analyze","properties":[{"name":"syft:package:foundBy","value":"github-actions-usage-cataloger"},{"name":"syft:package:type","value":"github-action"},{"name":"syft:cpe23","value":"cpe:2.3:a:github\\/codeql-action\\/analyze:github\\/codeql_action\\/analyze:v3:*:*:*:*:*:*:*"},{"name":"syft:cpe23","value":"cpe:2.3:a:github\\/codeql_action\\/analyze:github\\/codeql-action\\/analyze:v3:*:*:*:*:*:*:*"},{"name":"syft:cpe23","value":"cpe:2.3:a:github\\/codeql_action\\/analyze:github\\/codeql_action\\/analyze:v3:*:*:*:*:*:*:*"},{"name":"syft:cpe23","value":"cpe:2.3:a:github\\/codeql:github\\/codeql-action\\/analyze:v3:*:*:*:*:*:*:*"},{"name":"syft:cpe23","value":"cpe:2.3:a:github\\/codeql:github\\/codeql_action\\/analyze:v3:*:*:*:*:*:*:*"},{"name":"syft:location:0:path","value":"/.github/workflows/codeql-analysis.yml"}]},{"bom-ref":"pkg:github/github/codeql-action@v3?package-id=bb7c6d71b26ef8af#init","type":"library","name":"github/codeql-action/init","version":"v3","cpe":"cpe:2.3:a:github\\/codeql-action\\/init:github\\/codeql-action\\/init:v3:*:*:*:*:*:*:*","purl":"pkg:github/github/codeql-action@v3#init","properties":[{"name":"syft:package:foundBy","value":"github-actions-usage-cataloger"},{"name":"syft:package:type","value":"github-action"},{"name":"syft:cpe23","value":"cpe:2.3:a:github\\/codeql-action\\/init:github\\/codeql_action\\/init:v3:*:*:*:*:*:*:*"},{"name":"syft:cpe23","value":"cpe:2.3:a:github\\/codeql_action\\/init:github\\/codeql-action\\/init:v3:*:*:*:*:*:*:*"},{"name":"syft:cpe23","value":"cpe:2.3:a:github\\/codeql_action\\/init:github\\/codeql_action\\/init:v3:*:*:*:*:*:*:*"},{"name":"syft:cpe23","value":"cpe:2.3:a:github\\/codeql:github\\/codeql-action\\/init:v3:*:*:*:*:*:*:*"},{"name":"syft:cpe23","value":"cpe:2.3:a:github\\/codeql:github\\/codeql_action\\/init:v3:*:*:*:*:*:*:*"},{"name":"syft:location:0:path","value":"/.github/workflows/codeql-analysis.yml"}]},{"bom-ref":"pkg:github/microsoft/setup-msbuild@v2.0.0?package-id=c272240ab8a25ce7","type":"library","name":"microsoft/setup-msbuild","version":"v2.0.0","cpe":"cpe:2.3:a:microsoft\\/setup-msbuild:microsoft\\/setup-msbuild:v2.0.0:*:*:*:*:*:*:*","purl":"pkg:github/microsoft/setup-msbuild@v2.0.0","properties":[{"name":"syft:package:foundBy","value":"github-actions-usage-cataloger"},{"name":"syft:package:type","value":"github-action"},{"name":"syft:cpe23","value":"cpe:2.3:a:microsoft\\/setup-msbuild:microsoft\\/setup_msbuild:v2.0.0:*:*:*:*:*:*:*"},{"name":"syft:cpe23","value":"cpe:2.3:a:microsoft\\/setup_msbuild:microsoft\\/setup-msbuild:v2.0.0:*:*:*:*:*:*:*"},{"name":"syft:cpe23","value":"cpe:2.3:a:microsoft\\/setup_msbuild:microsoft\\/setup_msbuild:v2.0.0:*:*:*:*:*:*:*"},{"name":"syft:cpe23","value":"cpe:2.3:a:microsoft\\/setup:microsoft\\/setup-msbuild:v2.0.0:*:*:*:*:*:*:*"},{"name":"syft:cpe23","value":"cpe:2.3:a:microsoft\\/setup:microsoft\\/setup_msbuild:v2.0.0:*:*:*:*:*:*:*"},{"name":"syft:location:0:path","value":"/.github/workflows/codeql-analysis.yml"}]},{"bom-ref":"pkg:github/sigstore/cosign-installer@main?package-id=5bada9b45cd0bd59","type":"library","name":"sigstore/cosign-installer","version":"main","cpe":"cpe:2.3:a:sigstore\\/cosign-installer:sigstore\\/cosign-installer:main:*:*:*:*:*:*:*","purl":"pkg:github/sigstore/cosign-installer@main","properties":[{"name":"syft:package:foundBy","value":"github-actions-usage-cataloger"},{"name":"syft:package:type","value":"github-action"},{"name":"syft:cpe23","value":"cpe:2.3:a:sigstore\\/cosign-installer:sigstore\\/cosign_installer:main:*:*:*:*:*:*:*"},{"name":"syft:cpe23","value":"cpe:2.3:a:sigstore\\/cosign_installer:sigstore\\/cosign-installer:main:*:*:*:*:*:*:*"},{"name":"syft:cpe23","value":"cpe:2.3:a:sigstore\\/cosign_installer:sigstore\\/cosign_installer:main:*:*:*:*:*:*:*"},{"name":"syft:cpe23","value":"cpe:2.3:a:sigstore\\/cosign:sigstore\\/cosign-installer:main:*:*:*:*:*:*:*"},{"name":"syft:cpe23","value":"cpe:2.3:a:sigstore\\/cosign:sigstore\\/cosign_installer:main:*:*:*:*:*:*:*"},{"name":"syft:location:0:path","value":"/.github/workflows/docker-image.yml"}]}]}
